{"UNITID": {"column_title": "Unique identification number of the institution", "data": "117052", "data_processed": "Reedley College"}, "EFALEVEL": {"column_title": "Level of student", "data": "1", "data_processed": "1"}, "LINE": {"column_title": "Level of student (original line number on survey form)", "data": "29", "data_processed": "29"}, "SECTION": {"column_title": "Attendance status of student", "data": "3", "data_processed": "3"}, "LSTUDY": {"column_title": "Level of student", "data": "4", "data_processed": "4"}, "EFTOTLT": {"column_title": "Grand total", "data": "11296", "data_processed": "11296"}, "EFTOTLM": {"column_title": "Grand total men", "data": "4507", "data_processed": "4507"}, "EFTOTLW": {"column_title": "Grand total women", "data": "6789", "data_processed": "6789"}, "EFAIANT": {"column_title": "American Indian or Alaska Native total", "data": "49", "data_processed": "49"}, "EFAIANM": {"column_title": "American Indian or Alaska Native men", "data": "14", "data_processed": "14"}, "EFAIANW": {"column_title": "American Indian or Alaska Native women", "data": "35", "data_processed": "35"}, "EFASIAT": {"column_title": "Asian total", "data": "645", "data_processed": "645"}, "EFASIAM": {"column_title": "Asian men", "data": "274", "data_processed": "274"}, "EFASIAW": {"column_title": "Asian women", "data": "371", "data_processed": "371"}, "EFBKAAT": {"column_title": "Black or African American total", "data": "228", "data_processed": "228"}, "EFBKAAM": {"column_title": "Black or African American men", "data": "113", "data_processed": "113"}, "EFBKAAW": {"column_title": "Black or African American women", "data": "115", "data_processed": "115"}, "EFHISPT": {"column_title": "Hispanic total", "data": "8204", "data_processed": "8204"}, "EFHISPM": {"column_title": "Hispanic men", "data": "3186", "data_processed": "3186"}, "EFHISPW": {"column_title": "Hispanic women", "data": "5018", "data_processed": "5018"}, "EFNHPIT": {"column_title": "Native Hawaiian or Other Pacific Islander total", "data": "13", "data_processed": "13"}, "EFNHPIM": {"column_title": "Native Hawaiian or Other Pacific Islander men", "data": "6", "data_processed": "6"}, "EFNHPIW": {"column_title": "Native Hawaiian or Other Pacific Islander women", "data": "7", "data_processed": "7"}, "EFWHITT": {"column_title": "White total", "data": "1792", "data_processed": "1792"}, "EFWHITM": {"column_title": "White men", "data": "769", "data_processed": "769"}, "EFWHITW": {"column_title": "White women", "data": "1023", "data_processed": "1023"}, "EF2MORT": {"column_title": "Two or more races total", "data": "249", "data_processed": "249"}, "EF2MORM": {"column_title": "Two or more races men", "data": "95", "data_processed": "95"}, "EF2MORW": {"column_title": "Two or more races women", "data": "154", "data_processed": "154"}, "EFUNKNT": {"column_title": "Race/ethnicity unknown total", "data": "114", "data_processed": "114"}, "EFUNKNM": {"column_title": "Race/ethnicity unknown men", "data": "49", "data_processed": "49"}, "EFUNKNW": {"column_title": "Race/ethnicity unknown women", "data": "65", "data_processed": "65"}, "EFNRALT": {"column_title": "Nonresident alien total", "data": "2", "data_processed": "2"}, "EFNRALM": {"column_title": "Nonresident alien men", "data": "1", "data_processed": "1"}, "EFNRALW": {"column_title": "Nonresident alien women", "data": "1", "data_processed": "1"}}