{"UNITID": {"column_title": "Unique identification number of the institution", "data": "123484", "data_processed": "College of the Siskiyous"}, "EFALEVEL": {"column_title": "Level of student", "data": "1", "data_processed": "1"}, "LINE": {"column_title": "Level of student (original line number on survey form)", "data": "29", "data_processed": "29"}, "SECTION": {"column_title": "Attendance status of student", "data": "3", "data_processed": "3"}, "LSTUDY": {"column_title": "Level of student", "data": "4", "data_processed": "4"}, "EFTOTLT": {"column_title": "Grand total", "data": "1761", "data_processed": "1761"}, "EFTOTLM": {"column_title": "Grand total men", "data": "847", "data_processed": "847"}, "EFTOTLW": {"column_title": "Grand total women", "data": "914", "data_processed": "914"}, "EFAIANT": {"column_title": "American Indian or Alaska Native total", "data": "54", "data_processed": "54"}, "EFAIANM": {"column_title": "American Indian or Alaska Native men", "data": "13", "data_processed": "13"}, "EFAIANW": {"column_title": "American Indian or Alaska Native women", "data": "41", "data_processed": "41"}, "EFASIAT": {"column_title": "Asian total", "data": "58", "data_processed": "58"}, "EFASIAM": {"column_title": "Asian men", "data": "31", "data_processed": "31"}, "EFASIAW": {"column_title": "Asian women", "data": "27", "data_processed": "27"}, "EFBKAAT": {"column_title": "Black or African American total", "data": "87", "data_processed": "87"}, "EFBKAAM": {"column_title": "Black or African American men", "data": "68", "data_processed": "68"}, "EFBKAAW": {"column_title": "Black or African American women", "data": "19", "data_processed": "19"}, "EFHISPT": {"column_title": "Hispanic total", "data": "330", "data_processed": "330"}, "EFHISPM": {"column_title": "Hispanic men", "data": "152", "data_processed": "152"}, "EFHISPW": {"column_title": "Hispanic women", "data": "178", "data_processed": "178"}, "EFNHPIT": {"column_title": "Native Hawaiian or Other Pacific Islander total", "data": "12", "data_processed": "12"}, "EFNHPIM": {"column_title": "Native Hawaiian or Other Pacific Islander men", "data": "11", "data_processed": "11"}, "EFNHPIW": {"column_title": "Native Hawaiian or Other Pacific Islander women", "data": "1", "data_processed": "1"}, "EFWHITT": {"column_title": "White total", "data": "947", "data_processed": "947"}, "EFWHITM": {"column_title": "White men", "data": "430", "data_processed": "430"}, "EFWHITW": {"column_title": "White women", "data": "517", "data_processed": "517"}, "EF2MORT": {"column_title": "Two or more races total", "data": "129", "data_processed": "129"}, "EF2MORM": {"column_title": "Two or more races men", "data": "59", "data_processed": "59"}, "EF2MORW": {"column_title": "Two or more races women", "data": "70", "data_processed": "70"}, "EFUNKNT": {"column_title": "Race/ethnicity unknown total", "data": "136", "data_processed": "136"}, "EFUNKNM": {"column_title": "Race/ethnicity unknown men", "data": "78", "data_processed": "78"}, "EFUNKNW": {"column_title": "Race/ethnicity unknown women", "data": "58", "data_processed": "58"}, "EFNRALT": {"column_title": "Nonresident alien total", "data": "8", "data_processed": "8"}, "EFNRALM": {"column_title": "Nonresident alien men", "data": "5", "data_processed": "5"}, "EFNRALW": {"column_title": "Nonresident alien women", "data": "3", "data_processed": "3"}}