{"UNITID": {"column_title": "Unique identification number of the institution", "data": "127060", "data_processed": "University of Denver"}, "EFALEVEL": {"column_title": "Level of student", "data": "1", "data_processed": "1"}, "LINE": {"column_title": "Level of student (original line number on survey form)", "data": "29", "data_processed": "29"}, "SECTION": {"column_title": "Attendance status of student", "data": "3", "data_processed": "3"}, "LSTUDY": {"column_title": "Level of student", "data": "4", "data_processed": "4"}, "EFTOTLT": {"column_title": "Grand total", "data": "12931", "data_processed": "12931"}, "EFTOTLM": {"column_title": "Grand total men", "data": "5172", "data_processed": "5172"}, "EFTOTLW": {"column_title": "Grand total women", "data": "7759", "data_processed": "7759"}, "EFAIANT": {"column_title": "American Indian or Alaska Native total", "data": "68", "data_processed": "68"}, "EFAIANM": {"column_title": "American Indian or Alaska Native men", "data": "23", "data_processed": "23"}, "EFAIANW": {"column_title": "American Indian or Alaska Native women", "data": "45", "data_processed": "45"}, "EFASIAT": {"column_title": "Asian total", "data": "475", "data_processed": "475"}, "EFASIAM": {"column_title": "Asian men", "data": "164", "data_processed": "164"}, "EFASIAW": {"column_title": "Asian women", "data": "311", "data_processed": "311"}, "EFBKAAT": {"column_title": "Black or African American total", "data": "522", "data_processed": "522"}, "EFBKAAM": {"column_title": "Black or African American men", "data": "196", "data_processed": "196"}, "EFBKAAW": {"column_title": "Black or African American women", "data": "326", "data_processed": "326"}, "EFHISPT": {"column_title": "Hispanic total", "data": "1575", "data_processed": "1575"}, "EFHISPM": {"column_title": "Hispanic men", "data": "540", "data_processed": "540"}, "EFHISPW": {"column_title": "Hispanic women", "data": "1035", "data_processed": "1035"}, "EFNHPIT": {"column_title": "Native Hawaiian or Other Pacific Islander total", "data": "19", "data_processed": "19"}, "EFNHPIM": {"column_title": "Native Hawaiian or Other Pacific Islander men", "data": "8", "data_processed": "8"}, "EFNHPIW": {"column_title": "Native Hawaiian or Other Pacific Islander women", "data": "11", "data_processed": "11"}, "EFWHITT": {"column_title": "White total", "data": "8682", "data_processed": "8682"}, "EFWHITM": {"column_title": "White men", "data": "3478", "data_processed": "3478"}, "EFWHITW": {"column_title": "White women", "data": "5204", "data_processed": "5204"}, "EF2MORT": {"column_title": "Two or more races total", "data": "560", "data_processed": "560"}, "EF2MORM": {"column_title": "Two or more races men", "data": "230", "data_processed": "230"}, "EF2MORW": {"column_title": "Two or more races women", "data": "330", "data_processed": "330"}, "EFUNKNT": {"column_title": "Race/ethnicity unknown total", "data": "269", "data_processed": "269"}, "EFUNKNM": {"column_title": "Race/ethnicity unknown men", "data": "104", "data_processed": "104"}, "EFUNKNW": {"column_title": "Race/ethnicity unknown women", "data": "165", "data_processed": "165"}, "EFNRALT": {"column_title": "Nonresident alien total", "data": "761", "data_processed": "761"}, "EFNRALM": {"column_title": "Nonresident alien men", "data": "429", "data_processed": "429"}, "EFNRALW": {"column_title": "Nonresident alien women", "data": "332", "data_processed": "332"}}