{"UNITID": {"column_title": "Unique identification number of the institution", "data": "130396", "data_processed": "Gateway Community College"}, "EFALEVEL": {"column_title": "Level of student", "data": "1", "data_processed": "1"}, "LINE": {"column_title": "Level of student (original line number on survey form)", "data": "29", "data_processed": "29"}, "SECTION": {"column_title": "Attendance status of student", "data": "3", "data_processed": "3"}, "LSTUDY": {"column_title": "Level of student", "data": "4", "data_processed": "4"}, "EFTOTLT": {"column_title": "Grand total", "data": "6864", "data_processed": "6864"}, "EFTOTLM": {"column_title": "Grand total men", "data": "2738", "data_processed": "2738"}, "EFTOTLW": {"column_title": "Grand total women", "data": "4126", "data_processed": "4126"}, "EFAIANT": {"column_title": "American Indian or Alaska Native total", "data": "15", "data_processed": "15"}, "EFAIANM": {"column_title": "American Indian or Alaska Native men", "data": "6", "data_processed": "6"}, "EFAIANW": {"column_title": "American Indian or Alaska Native women", "data": "9", "data_processed": "9"}, "EFASIAT": {"column_title": "Asian total", "data": "286", "data_processed": "286"}, "EFASIAM": {"column_title": "Asian men", "data": "127", "data_processed": "127"}, "EFASIAW": {"column_title": "Asian women", "data": "159", "data_processed": "159"}, "EFBKAAT": {"column_title": "Black or African American total", "data": "1688", "data_processed": "1688"}, "EFBKAAM": {"column_title": "Black or African American men", "data": "615", "data_processed": "615"}, "EFBKAAW": {"column_title": "Black or African American women", "data": "1073", "data_processed": "1073"}, "EFHISPT": {"column_title": "Hispanic total", "data": "1956", "data_processed": "1956"}, "EFHISPM": {"column_title": "Hispanic men", "data": "705", "data_processed": "705"}, "EFHISPW": {"column_title": "Hispanic women", "data": "1251", "data_processed": "1251"}, "EFNHPIT": {"column_title": "Native Hawaiian or Other Pacific Islander total", "data": "12", "data_processed": "12"}, "EFNHPIM": {"column_title": "Native Hawaiian or Other Pacific Islander men", "data": "4", "data_processed": "4"}, "EFNHPIW": {"column_title": "Native Hawaiian or Other Pacific Islander women", "data": "8", "data_processed": "8"}, "EFWHITT": {"column_title": "White total", "data": "2533", "data_processed": "2533"}, "EFWHITM": {"column_title": "White men", "data": "1105", "data_processed": "1105"}, "EFWHITW": {"column_title": "White women", "data": "1428", "data_processed": "1428"}, "EF2MORT": {"column_title": "Two or more races total", "data": "194", "data_processed": "194"}, "EF2MORM": {"column_title": "Two or more races men", "data": "84", "data_processed": "84"}, "EF2MORW": {"column_title": "Two or more races women", "data": "110", "data_processed": "110"}, "EFUNKNT": {"column_title": "Race/ethnicity unknown total", "data": "142", "data_processed": "142"}, "EFUNKNM": {"column_title": "Race/ethnicity unknown men", "data": "70", "data_processed": "70"}, "EFUNKNW": {"column_title": "Race/ethnicity unknown women", "data": "72", "data_processed": "72"}, "EFNRALT": {"column_title": "Nonresident alien total", "data": "38", "data_processed": "38"}, "EFNRALM": {"column_title": "Nonresident alien men", "data": "22", "data_processed": "22"}, "EFNRALW": {"column_title": "Nonresident alien women", "data": "16", "data_processed": "16"}}