{"UNITID": {"column_title": "Unique identification number of the institution", "data": "133650", "data_processed": "Florida Agricultural and Mechanical University"}, "EFALEVEL": {"column_title": "Level of student", "data": "1", "data_processed": "1"}, "LINE": {"column_title": "Level of student (original line number on survey form)", "data": "29", "data_processed": "29"}, "SECTION": {"column_title": "Attendance status of student", "data": "3", "data_processed": "3"}, "LSTUDY": {"column_title": "Level of student", "data": "4", "data_processed": "4"}, "EFTOTLT": {"column_title": "Grand total", "data": "9626", "data_processed": "9626"}, "EFTOTLM": {"column_title": "Grand total men", "data": "3370", "data_processed": "3370"}, "EFTOTLW": {"column_title": "Grand total women", "data": "6256", "data_processed": "6256"}, "EFAIANT": {"column_title": "American Indian or Alaska Native total", "data": "2", "data_processed": "2"}, "EFAIANM": {"column_title": "American Indian or Alaska Native men", "data": "0", "data_processed": "0"}, "EFAIANW": {"column_title": "American Indian or Alaska Native women", "data": "2", "data_processed": "2"}, "EFASIAT": {"column_title": "Asian total", "data": "81", "data_processed": "81"}, "EFASIAM": {"column_title": "Asian men", "data": "37", "data_processed": "37"}, "EFASIAW": {"column_title": "Asian women", "data": "44", "data_processed": "44"}, "EFBKAAT": {"column_title": "Black or African American total", "data": "7966", "data_processed": "7966"}, "EFBKAAM": {"column_title": "Black or African American men", "data": "2661", "data_processed": "2661"}, "EFBKAAW": {"column_title": "Black or African American women", "data": "5305", "data_processed": "5305"}, "EFHISPT": {"column_title": "Hispanic total", "data": "476", "data_processed": "476"}, "EFHISPM": {"column_title": "Hispanic men", "data": "182", "data_processed": "182"}, "EFHISPW": {"column_title": "Hispanic women", "data": "294", "data_processed": "294"}, "EFNHPIT": {"column_title": "Native Hawaiian or Other Pacific Islander total", "data": "4", "data_processed": "4"}, "EFNHPIM": {"column_title": "Native Hawaiian or Other Pacific Islander men", "data": "2", "data_processed": "2"}, "EFNHPIW": {"column_title": "Native Hawaiian or Other Pacific Islander women", "data": "2", "data_processed": "2"}, "EFWHITT": {"column_title": "White total", "data": "706", "data_processed": "706"}, "EFWHITM": {"column_title": "White men", "data": "352", "data_processed": "352"}, "EFWHITW": {"column_title": "White women", "data": "354", "data_processed": "354"}, "EF2MORT": {"column_title": "Two or more races total", "data": "313", "data_processed": "313"}, "EF2MORM": {"column_title": "Two or more races men", "data": "100", "data_processed": "100"}, "EF2MORW": {"column_title": "Two or more races women", "data": "213", "data_processed": "213"}, "EFUNKNT": {"column_title": "Race/ethnicity unknown total", "data": "2", "data_processed": "2"}, "EFUNKNM": {"column_title": "Race/ethnicity unknown men", "data": "0", "data_processed": "0"}, "EFUNKNW": {"column_title": "Race/ethnicity unknown women", "data": "2", "data_processed": "2"}, "EFNRALT": {"column_title": "Nonresident alien total", "data": "76", "data_processed": "76"}, "EFNRALM": {"column_title": "Nonresident alien men", "data": "36", "data_processed": "36"}, "EFNRALW": {"column_title": "Nonresident alien women", "data": "40", "data_processed": "40"}}