{"UNITID": {"column_title": "Unique identification number of the institution", "data": "153144", "data_processed": "Coe College"}, "EFALEVEL": {"column_title": "Level of student", "data": "1", "data_processed": "1"}, "LINE": {"column_title": "Level of student (original line number on survey form)", "data": "29", "data_processed": "29"}, "SECTION": {"column_title": "Attendance status of student", "data": "3", "data_processed": "3"}, "LSTUDY": {"column_title": "Level of student", "data": "4", "data_processed": "4"}, "EFTOTLT": {"column_title": "Grand total", "data": "1430", "data_processed": "1430"}, "EFTOTLM": {"column_title": "Grand total men", "data": "646", "data_processed": "646"}, "EFTOTLW": {"column_title": "Grand total women", "data": "784", "data_processed": "784"}, "EFAIANT": {"column_title": "American Indian or Alaska Native total", "data": "6", "data_processed": "6"}, "EFAIANM": {"column_title": "American Indian or Alaska Native men", "data": "2", "data_processed": "2"}, "EFAIANW": {"column_title": "American Indian or Alaska Native women", "data": "4", "data_processed": "4"}, "EFASIAT": {"column_title": "Asian total", "data": "66", "data_processed": "66"}, "EFASIAM": {"column_title": "Asian men", "data": "30", "data_processed": "30"}, "EFASIAW": {"column_title": "Asian women", "data": "36", "data_processed": "36"}, "EFBKAAT": {"column_title": "Black or African American total", "data": "102", "data_processed": "102"}, "EFBKAAM": {"column_title": "Black or African American men", "data": "39", "data_processed": "39"}, "EFBKAAW": {"column_title": "Black or African American women", "data": "63", "data_processed": "63"}, "EFHISPT": {"column_title": "Hispanic total", "data": "161", "data_processed": "161"}, "EFHISPM": {"column_title": "Hispanic men", "data": "68", "data_processed": "68"}, "EFHISPW": {"column_title": "Hispanic women", "data": "93", "data_processed": "93"}, "EFNHPIT": {"column_title": "Native Hawaiian or Other Pacific Islander total", "data": "2", "data_processed": "2"}, "EFNHPIM": {"column_title": "Native Hawaiian or Other Pacific Islander men", "data": "2", "data_processed": "2"}, "EFNHPIW": {"column_title": "Native Hawaiian or Other Pacific Islander women", "data": "0", "data_processed": "0"}, "EFWHITT": {"column_title": "White total", "data": "938", "data_processed": "938"}, "EFWHITM": {"column_title": "White men", "data": "443", "data_processed": "443"}, "EFWHITW": {"column_title": "White women", "data": "495", "data_processed": "495"}, "EF2MORT": {"column_title": "Two or more races total", "data": "36", "data_processed": "36"}, "EF2MORM": {"column_title": "Two or more races men", "data": "11", "data_processed": "11"}, "EF2MORW": {"column_title": "Two or more races women", "data": "25", "data_processed": "25"}, "EFUNKNT": {"column_title": "Race/ethnicity unknown total", "data": "93", "data_processed": "93"}, "EFUNKNM": {"column_title": "Race/ethnicity unknown men", "data": "42", "data_processed": "42"}, "EFUNKNW": {"column_title": "Race/ethnicity unknown women", "data": "51", "data_processed": "51"}, "EFNRALT": {"column_title": "Nonresident alien total", "data": "26", "data_processed": "26"}, "EFNRALM": {"column_title": "Nonresident alien men", "data": "9", "data_processed": "9"}, "EFNRALW": {"column_title": "Nonresident alien women", "data": "17", "data_processed": "17"}}