{"UNITID": {"column_title": "Unique identification number of the institution", "data": "175883", "data_processed": "Jones County Junior College"}, "EFALEVEL": {"column_title": "Level of student", "data": "1", "data_processed": "1"}, "LINE": {"column_title": "Level of student (original line number on survey form)", "data": "29", "data_processed": "29"}, "SECTION": {"column_title": "Attendance status of student", "data": "3", "data_processed": "3"}, "LSTUDY": {"column_title": "Level of student", "data": "4", "data_processed": "4"}, "EFTOTLT": {"column_title": "Grand total", "data": "4536", "data_processed": "4536"}, "EFTOTLM": {"column_title": "Grand total men", "data": "1779", "data_processed": "1779"}, "EFTOTLW": {"column_title": "Grand total women", "data": "2757", "data_processed": "2757"}, "EFAIANT": {"column_title": "American Indian or Alaska Native total", "data": "38", "data_processed": "38"}, "EFAIANM": {"column_title": "American Indian or Alaska Native men", "data": "15", "data_processed": "15"}, "EFAIANW": {"column_title": "American Indian or Alaska Native women", "data": "23", "data_processed": "23"}, "EFASIAT": {"column_title": "Asian total", "data": "26", "data_processed": "26"}, "EFASIAM": {"column_title": "Asian men", "data": "11", "data_processed": "11"}, "EFASIAW": {"column_title": "Asian women", "data": "15", "data_processed": "15"}, "EFBKAAT": {"column_title": "Black or African American total", "data": "1378", "data_processed": "1378"}, "EFBKAAM": {"column_title": "Black or African American men", "data": "464", "data_processed": "464"}, "EFBKAAW": {"column_title": "Black or African American women", "data": "914", "data_processed": "914"}, "EFHISPT": {"column_title": "Hispanic total", "data": "50", "data_processed": "50"}, "EFHISPM": {"column_title": "Hispanic men", "data": "22", "data_processed": "22"}, "EFHISPW": {"column_title": "Hispanic women", "data": "28", "data_processed": "28"}, "EFNHPIT": {"column_title": "Native Hawaiian or Other Pacific Islander total", "data": "5", "data_processed": "5"}, "EFNHPIM": {"column_title": "Native Hawaiian or Other Pacific Islander men", "data": "3", "data_processed": "3"}, "EFNHPIW": {"column_title": "Native Hawaiian or Other Pacific Islander women", "data": "2", "data_processed": "2"}, "EFWHITT": {"column_title": "White total", "data": "2933", "data_processed": "2933"}, "EFWHITM": {"column_title": "White men", "data": "1220", "data_processed": "1220"}, "EFWHITW": {"column_title": "White women", "data": "1713", "data_processed": "1713"}, "EF2MORT": {"column_title": "Two or more races total", "data": "77", "data_processed": "77"}, "EF2MORM": {"column_title": "Two or more races men", "data": "30", "data_processed": "30"}, "EF2MORW": {"column_title": "Two or more races women", "data": "47", "data_processed": "47"}, "EFUNKNT": {"column_title": "Race/ethnicity unknown total", "data": "29", "data_processed": "29"}, "EFUNKNM": {"column_title": "Race/ethnicity unknown men", "data": "14", "data_processed": "14"}, "EFUNKNW": {"column_title": "Race/ethnicity unknown women", "data": "15", "data_processed": "15"}, "EFNRALT": {"column_title": "Nonresident alien total", "data": "0", "data_processed": "0"}, "EFNRALM": {"column_title": "Nonresident alien men", "data": "0", "data_processed": "0"}, "EFNRALW": {"column_title": "Nonresident alien women", "data": "0", "data_processed": "0"}}