{"UNITID": {"column_title": "Unique identification number of the institution", "data": "185129", "data_processed": "New Jersey City University"}, "EFALEVEL": {"column_title": "Level of student", "data": "1", "data_processed": "1"}, "LINE": {"column_title": "Level of student (original line number on survey form)", "data": "29", "data_processed": "29"}, "SECTION": {"column_title": "Attendance status of student", "data": "3", "data_processed": "3"}, "LSTUDY": {"column_title": "Level of student", "data": "4", "data_processed": "4"}, "EFTOTLT": {"column_title": "Grand total", "data": "7949", "data_processed": "7949"}, "EFTOTLM": {"column_title": "Grand total men", "data": "3038", "data_processed": "3038"}, "EFTOTLW": {"column_title": "Grand total women", "data": "4911", "data_processed": "4911"}, "EFAIANT": {"column_title": "American Indian or Alaska Native total", "data": "29", "data_processed": "29"}, "EFAIANM": {"column_title": "American Indian or Alaska Native men", "data": "12", "data_processed": "12"}, "EFAIANW": {"column_title": "American Indian or Alaska Native women", "data": "17", "data_processed": "17"}, "EFASIAT": {"column_title": "Asian total", "data": "590", "data_processed": "590"}, "EFASIAM": {"column_title": "Asian men", "data": "255", "data_processed": "255"}, "EFASIAW": {"column_title": "Asian women", "data": "335", "data_processed": "335"}, "EFBKAAT": {"column_title": "Black or African American total", "data": "1736", "data_processed": "1736"}, "EFBKAAM": {"column_title": "Black or African American men", "data": "627", "data_processed": "627"}, "EFBKAAW": {"column_title": "Black or African American women", "data": "1109", "data_processed": "1109"}, "EFHISPT": {"column_title": "Hispanic total", "data": "2855", "data_processed": "2855"}, "EFHISPM": {"column_title": "Hispanic men", "data": "1049", "data_processed": "1049"}, "EFHISPW": {"column_title": "Hispanic women", "data": "1806", "data_processed": "1806"}, "EFNHPIT": {"column_title": "Native Hawaiian or Other Pacific Islander total", "data": "35", "data_processed": "35"}, "EFNHPIM": {"column_title": "Native Hawaiian or Other Pacific Islander men", "data": "16", "data_processed": "16"}, "EFNHPIW": {"column_title": "Native Hawaiian or Other Pacific Islander women", "data": "19", "data_processed": "19"}, "EFWHITT": {"column_title": "White total", "data": "1906", "data_processed": "1906"}, "EFWHITM": {"column_title": "White men", "data": "764", "data_processed": "764"}, "EFWHITW": {"column_title": "White women", "data": "1142", "data_processed": "1142"}, "EF2MORT": {"column_title": "Two or more races total", "data": "168", "data_processed": "168"}, "EF2MORM": {"column_title": "Two or more races men", "data": "72", "data_processed": "72"}, "EF2MORW": {"column_title": "Two or more races women", "data": "96", "data_processed": "96"}, "EFUNKNT": {"column_title": "Race/ethnicity unknown total", "data": "457", "data_processed": "457"}, "EFUNKNM": {"column_title": "Race/ethnicity unknown men", "data": "174", "data_processed": "174"}, "EFUNKNW": {"column_title": "Race/ethnicity unknown women", "data": "283", "data_processed": "283"}, "EFNRALT": {"column_title": "Nonresident alien total", "data": "173", "data_processed": "173"}, "EFNRALM": {"column_title": "Nonresident alien men", "data": "69", "data_processed": "69"}, "EFNRALW": {"column_title": "Nonresident alien women", "data": "104", "data_processed": "104"}}