{"UNITID": {"column_title": "Unique identification number of the institution", "data": "191968", "data_processed": "Ithaca College"}, "EFALEVEL": {"column_title": "Level of student", "data": "1", "data_processed": "1"}, "LINE": {"column_title": "Level of student (original line number on survey form)", "data": "29", "data_processed": "29"}, "SECTION": {"column_title": "Attendance status of student", "data": "3", "data_processed": "3"}, "LSTUDY": {"column_title": "Level of student", "data": "4", "data_processed": "4"}, "EFTOTLT": {"column_title": "Grand total", "data": "6266", "data_processed": "6266"}, "EFTOTLM": {"column_title": "Grand total men", "data": "2605", "data_processed": "2605"}, "EFTOTLW": {"column_title": "Grand total women", "data": "3661", "data_processed": "3661"}, "EFAIANT": {"column_title": "American Indian or Alaska Native total", "data": "8", "data_processed": "8"}, "EFAIANM": {"column_title": "American Indian or Alaska Native men", "data": "3", "data_processed": "3"}, "EFAIANW": {"column_title": "American Indian or Alaska Native women", "data": "5", "data_processed": "5"}, "EFASIAT": {"column_title": "Asian total", "data": "260", "data_processed": "260"}, "EFASIAM": {"column_title": "Asian men", "data": "95", "data_processed": "95"}, "EFASIAW": {"column_title": "Asian women", "data": "165", "data_processed": "165"}, "EFBKAAT": {"column_title": "Black or African American total", "data": "350", "data_processed": "350"}, "EFBKAAM": {"column_title": "Black or African American men", "data": "149", "data_processed": "149"}, "EFBKAAW": {"column_title": "Black or African American women", "data": "201", "data_processed": "201"}, "EFHISPT": {"column_title": "Hispanic total", "data": "562", "data_processed": "562"}, "EFHISPM": {"column_title": "Hispanic men", "data": "229", "data_processed": "229"}, "EFHISPW": {"column_title": "Hispanic women", "data": "333", "data_processed": "333"}, "EFNHPIT": {"column_title": "Native Hawaiian or Other Pacific Islander total", "data": "3", "data_processed": "3"}, "EFNHPIM": {"column_title": "Native Hawaiian or Other Pacific Islander men", "data": "1", "data_processed": "1"}, "EFNHPIW": {"column_title": "Native Hawaiian or Other Pacific Islander women", "data": "2", "data_processed": "2"}, "EFWHITT": {"column_title": "White total", "data": "4568", "data_processed": "4568"}, "EFWHITM": {"column_title": "White men", "data": "1915", "data_processed": "1915"}, "EFWHITW": {"column_title": "White women", "data": "2653", "data_processed": "2653"}, "EF2MORT": {"column_title": "Two or more races total", "data": "211", "data_processed": "211"}, "EF2MORM": {"column_title": "Two or more races men", "data": "81", "data_processed": "81"}, "EF2MORW": {"column_title": "Two or more races women", "data": "130", "data_processed": "130"}, "EFUNKNT": {"column_title": "Race/ethnicity unknown total", "data": "174", "data_processed": "174"}, "EFUNKNM": {"column_title": "Race/ethnicity unknown men", "data": "72", "data_processed": "72"}, "EFUNKNW": {"column_title": "Race/ethnicity unknown women", "data": "102", "data_processed": "102"}, "EFNRALT": {"column_title": "Nonresident alien total", "data": "130", "data_processed": "130"}, "EFNRALM": {"column_title": "Nonresident alien men", "data": "60", "data_processed": "60"}, "EFNRALW": {"column_title": "Nonresident alien women", "data": "70", "data_processed": "70"}}