{"UNITID": {"column_title": "Unique identification number of the institution", "data": "217484", "data_processed": "University of Rhode Island"}, "EFALEVEL": {"column_title": "Level of student", "data": "1", "data_processed": "1"}, "LINE": {"column_title": "Level of student (original line number on survey form)", "data": "29", "data_processed": "29"}, "SECTION": {"column_title": "Attendance status of student", "data": "3", "data_processed": "3"}, "LSTUDY": {"column_title": "Level of student", "data": "4", "data_processed": "4"}, "EFTOTLT": {"column_title": "Grand total", "data": "17465", "data_processed": "17465"}, "EFTOTLM": {"column_title": "Grand total men", "data": "7566", "data_processed": "7566"}, "EFTOTLW": {"column_title": "Grand total women", "data": "9899", "data_processed": "9899"}, "EFAIANT": {"column_title": "American Indian or Alaska Native total", "data": "38", "data_processed": "38"}, "EFAIANM": {"column_title": "American Indian or Alaska Native men", "data": "15", "data_processed": "15"}, "EFAIANW": {"column_title": "American Indian or Alaska Native women", "data": "23", "data_processed": "23"}, "EFASIAT": {"column_title": "Asian total", "data": "630", "data_processed": "630"}, "EFASIAM": {"column_title": "Asian men", "data": "287", "data_processed": "287"}, "EFASIAW": {"column_title": "Asian women", "data": "343", "data_processed": "343"}, "EFBKAAT": {"column_title": "Black or African American total", "data": "835", "data_processed": "835"}, "EFBKAAM": {"column_title": "Black or African American men", "data": "389", "data_processed": "389"}, "EFBKAAW": {"column_title": "Black or African American women", "data": "446", "data_processed": "446"}, "EFHISPT": {"column_title": "Hispanic total", "data": "1641", "data_processed": "1641"}, "EFHISPM": {"column_title": "Hispanic men", "data": "665", "data_processed": "665"}, "EFHISPW": {"column_title": "Hispanic women", "data": "976", "data_processed": "976"}, "EFNHPIT": {"column_title": "Native Hawaiian or Other Pacific Islander total", "data": "16", "data_processed": "16"}, "EFNHPIM": {"column_title": "Native Hawaiian or Other Pacific Islander men", "data": "7", "data_processed": "7"}, "EFNHPIW": {"column_title": "Native Hawaiian or Other Pacific Islander women", "data": "9", "data_processed": "9"}, "EFWHITT": {"column_title": "White total", "data": "12330", "data_processed": "12330"}, "EFWHITM": {"column_title": "White men", "data": "5297", "data_processed": "5297"}, "EFWHITW": {"column_title": "White women", "data": "7033", "data_processed": "7033"}, "EF2MORT": {"column_title": "Two or more races total", "data": "454", "data_processed": "454"}, "EF2MORM": {"column_title": "Two or more races men", "data": "205", "data_processed": "205"}, "EF2MORW": {"column_title": "Two or more races women", "data": "249", "data_processed": "249"}, "EFUNKNT": {"column_title": "Race/ethnicity unknown total", "data": "1026", "data_processed": "1026"}, "EFUNKNM": {"column_title": "Race/ethnicity unknown men", "data": "456", "data_processed": "456"}, "EFUNKNW": {"column_title": "Race/ethnicity unknown women", "data": "570", "data_processed": "570"}, "EFNRALT": {"column_title": "Nonresident alien total", "data": "495", "data_processed": "495"}, "EFNRALM": {"column_title": "Nonresident alien men", "data": "245", "data_processed": "245"}, "EFNRALW": {"column_title": "Nonresident alien women", "data": "250", "data_processed": "250"}}