{"UNITID": {"column_title": "Unique identification number of the institution", "data": "222062", "data_processed": "Walters State Community College"}, "EFALEVEL": {"column_title": "Level of student", "data": "1", "data_processed": "1"}, "LINE": {"column_title": "Level of student (original line number on survey form)", "data": "29", "data_processed": "29"}, "SECTION": {"column_title": "Attendance status of student", "data": "3", "data_processed": "3"}, "LSTUDY": {"column_title": "Level of student", "data": "4", "data_processed": "4"}, "EFTOTLT": {"column_title": "Grand total", "data": "6279", "data_processed": "6279"}, "EFTOTLM": {"column_title": "Grand total men", "data": "2254", "data_processed": "2254"}, "EFTOTLW": {"column_title": "Grand total women", "data": "4025", "data_processed": "4025"}, "EFAIANT": {"column_title": "American Indian or Alaska Native total", "data": "21", "data_processed": "21"}, "EFAIANM": {"column_title": "American Indian or Alaska Native men", "data": "9", "data_processed": "9"}, "EFAIANW": {"column_title": "American Indian or Alaska Native women", "data": "12", "data_processed": "12"}, "EFASIAT": {"column_title": "Asian total", "data": "77", "data_processed": "77"}, "EFASIAM": {"column_title": "Asian men", "data": "38", "data_processed": "38"}, "EFASIAW": {"column_title": "Asian women", "data": "39", "data_processed": "39"}, "EFBKAAT": {"column_title": "Black or African American total", "data": "139", "data_processed": "139"}, "EFBKAAM": {"column_title": "Black or African American men", "data": "62", "data_processed": "62"}, "EFBKAAW": {"column_title": "Black or African American women", "data": "77", "data_processed": "77"}, "EFHISPT": {"column_title": "Hispanic total", "data": "337", "data_processed": "337"}, "EFHISPM": {"column_title": "Hispanic men", "data": "128", "data_processed": "128"}, "EFHISPW": {"column_title": "Hispanic women", "data": "209", "data_processed": "209"}, "EFNHPIT": {"column_title": "Native Hawaiian or Other Pacific Islander total", "data": "5", "data_processed": "5"}, "EFNHPIM": {"column_title": "Native Hawaiian or Other Pacific Islander men", "data": "2", "data_processed": "2"}, "EFNHPIW": {"column_title": "Native Hawaiian or Other Pacific Islander women", "data": "3", "data_processed": "3"}, "EFWHITT": {"column_title": "White total", "data": "5505", "data_processed": "5505"}, "EFWHITM": {"column_title": "White men", "data": "1931", "data_processed": "1931"}, "EFWHITW": {"column_title": "White women", "data": "3574", "data_processed": "3574"}, "EF2MORT": {"column_title": "Two or more races total", "data": "154", "data_processed": "154"}, "EF2MORM": {"column_title": "Two or more races men", "data": "66", "data_processed": "66"}, "EF2MORW": {"column_title": "Two or more races women", "data": "88", "data_processed": "88"}, "EFUNKNT": {"column_title": "Race/ethnicity unknown total", "data": "19", "data_processed": "19"}, "EFUNKNM": {"column_title": "Race/ethnicity unknown men", "data": "10", "data_processed": "10"}, "EFUNKNW": {"column_title": "Race/ethnicity unknown women", "data": "9", "data_processed": "9"}, "EFNRALT": {"column_title": "Nonresident alien total", "data": "22", "data_processed": "22"}, "EFNRALM": {"column_title": "Nonresident alien men", "data": "8", "data_processed": "8"}, "EFNRALW": {"column_title": "Nonresident alien women", "data": "14", "data_processed": "14"}}