{"UNITID": {"column_title": "Unique identification number of the institution", "data": "236753", "data_processed": "Tacoma Community College"}, "EFALEVEL": {"column_title": "Level of student", "data": "1", "data_processed": "1"}, "LINE": {"column_title": "Level of student (original line number on survey form)", "data": "29", "data_processed": "29"}, "SECTION": {"column_title": "Attendance status of student", "data": "3", "data_processed": "3"}, "LSTUDY": {"column_title": "Level of student", "data": "4", "data_processed": "4"}, "EFTOTLT": {"column_title": "Grand total", "data": "6095", "data_processed": "6095"}, "EFTOTLM": {"column_title": "Grand total men", "data": "2142", "data_processed": "2142"}, "EFTOTLW": {"column_title": "Grand total women", "data": "3953", "data_processed": "3953"}, "EFAIANT": {"column_title": "American Indian or Alaska Native total", "data": "38", "data_processed": "38"}, "EFAIANM": {"column_title": "American Indian or Alaska Native men", "data": "5", "data_processed": "5"}, "EFAIANW": {"column_title": "American Indian or Alaska Native women", "data": "33", "data_processed": "33"}, "EFASIAT": {"column_title": "Asian total", "data": "426", "data_processed": "426"}, "EFASIAM": {"column_title": "Asian men", "data": "164", "data_processed": "164"}, "EFASIAW": {"column_title": "Asian women", "data": "262", "data_processed": "262"}, "EFBKAAT": {"column_title": "Black or African American total", "data": "448", "data_processed": "448"}, "EFBKAAM": {"column_title": "Black or African American men", "data": "139", "data_processed": "139"}, "EFBKAAW": {"column_title": "Black or African American women", "data": "309", "data_processed": "309"}, "EFHISPT": {"column_title": "Hispanic total", "data": "661", "data_processed": "661"}, "EFHISPM": {"column_title": "Hispanic men", "data": "248", "data_processed": "248"}, "EFHISPW": {"column_title": "Hispanic women", "data": "413", "data_processed": "413"}, "EFNHPIT": {"column_title": "Native Hawaiian or Other Pacific Islander total", "data": "56", "data_processed": "56"}, "EFNHPIM": {"column_title": "Native Hawaiian or Other Pacific Islander men", "data": "15", "data_processed": "15"}, "EFNHPIW": {"column_title": "Native Hawaiian or Other Pacific Islander women", "data": "41", "data_processed": "41"}, "EFWHITT": {"column_title": "White total", "data": "2723", "data_processed": "2723"}, "EFWHITM": {"column_title": "White men", "data": "932", "data_processed": "932"}, "EFWHITW": {"column_title": "White women", "data": "1791", "data_processed": "1791"}, "EF2MORT": {"column_title": "Two or more races total", "data": "546", "data_processed": "546"}, "EF2MORM": {"column_title": "Two or more races men", "data": "161", "data_processed": "161"}, "EF2MORW": {"column_title": "Two or more races women", "data": "385", "data_processed": "385"}, "EFUNKNT": {"column_title": "Race/ethnicity unknown total", "data": "974", "data_processed": "974"}, "EFUNKNM": {"column_title": "Race/ethnicity unknown men", "data": "361", "data_processed": "361"}, "EFUNKNW": {"column_title": "Race/ethnicity unknown women", "data": "613", "data_processed": "613"}, "EFNRALT": {"column_title": "Nonresident alien total", "data": "223", "data_processed": "223"}, "EFNRALM": {"column_title": "Nonresident alien men", "data": "117", "data_processed": "117"}, "EFNRALW": {"column_title": "Nonresident alien women", "data": "106", "data_processed": "106"}}