{"UNITID": {"c_i": 0, "data": "233480", "d_p": "Bon Secours St Mary's Hospital School of Medical Imaging"}, "SCUGRAD": {"c_i": 2, "d_p": "29"}, "SCUGFFN": {"c_i": 4, "d_p": "0"}, "SCUGFFP": {"c_i": 6, "d_p": "0"}, "SCFY2": {"c_i": 30, "d_p": "29"}, "SCFY1N": {"c_i": 32, "d_p": "0"}, "SCFY1P": {"c_i": 34, "d_p": "0"}, "UAGRNTN": {"c_i": 36, "d_p": "6"}, "UAGRNTP": {"c_i": 38, "d_p": "21"}, "UAGRNTT": {"c_i": 40, "d_p": "29755"}, "UAGRNTA": {"c_i": 42, "d_p": "4959"}, "UPGRNTN": {"c_i": 44, "d_p": "6"}, "UPGRNTP": {"c_i": 46, "d_p": "21"}, "UPGRNTT": {"c_i": 48, "d_p": "29755"}, "UPGRNTA": {"c_i": 50, "d_p": "4959"}, "UFLOANN": {"c_i": 52, "d_p": "17"}, "UFLOANP": {"c_i": 54, "d_p": "59"}, "UFLOANT": {"c_i": 56, "d_p": "110026"}, "UFLOANA": {"c_i": 58, "d_p": "6472"}}